browser_launcher/__init__.py
browser_launcher/alt_browsers_tab.py
browser_launcher/alternative_browser_manager.py
browser_launcher/browser_tab.py
browser_launcher/chrome_tab.py
browser_launcher/cli.py
browser_launcher/components.py
browser_launcher/firefox_tab.py
browser_launcher/profile_manager.py
browser_launcher/styles.py
browser_launcher-0.0.1.dist-info/licenses/LICENSE
browser_launcher-0.0.1.dist-info/METADATA
browser_launcher-0.0.1.dist-info/WHEEL
browser_launcher-0.0.1.dist-info/entry_points.txt
browser_launcher-0.0.1.dist-info/top_level.txt
browser_launcher-0.0.1.dist-info/RECORD
