Metadata-Version: 2.4
Name: browser_launcher
Version: 0.0.1
Summary: A utility for launching browsers with specific profiles, URLs, and incognito mode from Python or the command line.
Author-email: Yusef Ulum <yusef314159@gmail.com>
License-Expression: MIT
Project-URL: Homepage, https://github.com/mexyusef/browser_launcher
Classifier: Development Status :: 3 - Alpha
Classifier: Intended Audience :: End Users/Desktop
Classifier: Programming Language :: Python :: 3
Classifier: Programming Language :: Python :: 3.8
Classifier: Programming Language :: Python :: 3.9
Classifier: Programming Language :: Python :: 3.10
Classifier: Operating System :: Microsoft :: Windows
Classifier: Operating System :: POSIX :: Linux
Classifier: Operating System :: MacOS
Classifier: Topic :: Utilities
Requires-Python: >=3.8
License-File: LICENSE
Dynamic: license-file
